setup.py
scrapr/__init__.py
scrapr/doc_attributes.py
scrapr/extractor.py
scrapr.egg-info/PKG-INFO
scrapr.egg-info/SOURCES.txt
scrapr.egg-info/dependency_links.txt
scrapr.egg-info/not-zip-safe
scrapr.egg-info/requires.txt
scrapr.egg-info/top_level.txt
scrapr/content/__init__.py
scrapr/content/base.py
scrapr/content/bs3.py
scrapr/content/bs4.py
scraprtest/__init__.py
scraprtest/doc_attributes.py
scraprtest/extractors.py
scraprtest/utils.py