Metadata-Version: 1.1
Name: scrapr
Version: 0.1.1
Summary: Scrapr makes it easy to setup a model for finding specific tags, links, or text on a web page.
Home-page: https://bitbucket.org/brianjinwright/scrapr
Author: Brian Jinwright
Author-email: team@ipoots.com
License: MIT
Keywords: web,scraping
Platform: UNKNOWN
Classifier: Programming Language :: Python
Classifier: Topic :: Software Development :: Libraries :: Python Modules
Classifier: Environment :: Web Environment
